anhelper/__init__.py
anhelper/adb.py
anhelper/common.py
anhelper/demo.py
anhelper/device.py
anhelper/ime.py
anhelper/minicap.py
anhelper/minitouch.py
anhelper/version.py
anhelper/prebuild/ADBKeyboard.apk
anhelper/prebuild/README.md
anhelper/prebuild/minicap/run.sh
anhelper/prebuild/minicap/arm64-v8a/bin/minicap
anhelper/prebuild/minicap/arm64-v8a/bin/minicap-nopie
anhelper/prebuild/minicap/arm64-v8a/lib/android-21/minicap.so
anhelper/prebuild/minicap/arm64-v8a/lib/android-22/minicap.so
anhelper/prebuild/minicap/arm64-v8a/lib/android-23/minicap.so
anhelper/prebuild/minicap/arm64-v8a/lib/android-24/minicap.so
anhelper/prebuild/minicap/arm64-v8a/lib/android-25/minicap.so
anhelper/prebuild/minicap/arm64-v8a/lib/android-26/minicap.so
anhelper/prebuild/minicap/arm64-v8a/lib/android-27/minicap.so
anhelper/prebuild/minicap/arm64-v8a/lib/android-28/minicap.so
anhelper/prebuild/minicap/arm64-v8a/lib/android-29/minicap.so
anhelper/prebuild/minicap/arm64-v8a/lib/android-30/minicap.so
anhelper/prebuild/minicap/arm64-v8a/lib/android-31/minicap.so
anhelper/prebuild/minicap/arm64-v8a/lib/android-32/minicap.so
anhelper/prebuild/minicap/armeabi-v7a/bin/minicap
anhelper/prebuild/minicap/armeabi-v7a/bin/minicap-nopie
anhelper/prebuild/minicap/armeabi-v7a/lib/android-10/minicap.so
anhelper/prebuild/minicap/armeabi-v7a/lib/android-14/minicap.so
anhelper/prebuild/minicap/armeabi-v7a/lib/android-15/minicap.so
anhelper/prebuild/minicap/armeabi-v7a/lib/android-16/minicap.so
anhelper/prebuild/minicap/armeabi-v7a/lib/android-17/minicap.so
anhelper/prebuild/minicap/armeabi-v7a/lib/android-18/minicap.so
anhelper/prebuild/minicap/armeabi-v7a/lib/android-19/minicap.so
anhelper/prebuild/minicap/armeabi-v7a/lib/android-21/minicap.so
anhelper/prebuild/minicap/armeabi-v7a/lib/android-22/minicap.so
anhelper/prebuild/minicap/armeabi-v7a/lib/android-23/minicap.so
anhelper/prebuild/minicap/armeabi-v7a/lib/android-24/minicap.so
anhelper/prebuild/minicap/armeabi-v7a/lib/android-25/minicap.so
anhelper-0.1.6.dist-info/LICENSE
anhelper-0.1.6.dist-info/METADATA
anhelper-0.1.6.dist-info/WHEEL
anhelper-0.1.6.dist-info/entry_points.txt
anhelper-0.1.6.dist-info/top_level.txt
anhelper-0.1.6.dist-info/RECORD
