Metadata-Version: 2.1
Name: anhelper
Version: 0.1.6
Summary: screencap, touch, remote control for android devices via adb
Home-page: https://github.com/zlolss/AnHelper
Author: zlols
Author-email: zlols@foxmail.com
License: MIT license
Keywords: test
Classifier: Programming Language :: Python :: 3 :: Only
Classifier: License :: OSI Approved :: MIT License
Requires-Python: >=3.0.0
License-File: LICENSE
Requires-Dist: adbutils
Requires-Dist: opencv-python
Requires-Dist: flask
Requires-Dist: socketman
